{
  "last_updated": "2026-05-22T03:59:31.887151+00:00",
  "total": 42,
  "hot_count": 0,
  "items": [
    {
      "id": "72b0b32704c8",
      "title": "Now Available on Steam - SCUM",
      "link": "https://store.steampowered.com/news/246601/",
      "source": "Steam",
      "hype_score": 0,
      "signals": [],
      "category": "indie",
      "fetched": "2026-05-22T03:59:31.886576+00:00"
    },
    {
      "id": "b0c491279ac2",
      "title": "Now Available on Steam - Foundation, 25% off!",
      "link": "https://store.steampowered.com/news/237790/",
      "source": "Steam",
      "hype_score": 0,
      "signals": [],
      "category": "indie",
      "fetched": "2026-05-22T03:59:31.886600+00:00"
    },
    {
      "id": "d21c8ee7bed6",
      "title": "Now Available on Steam - The Universim",
      "link": "https://store.steampowered.com/news/215594/",
      "source": "Steam",
      "hype_score": 0,
      "signals": [],
      "category": "indie",
      "fetched": "2026-05-22T03:59:31.886609+00:00"
    },
    {
      "id": "01ae24db1ea9",
      "title": "Now Available on Steam - Cowbots and Aliens",
      "link": "https://store.steampowered.com/news/214495/",
      "source": "Steam",
      "hype_score": 0,
      "signals": [],
      "category": "indie",
      "fetched": "2026-05-22T03:59:31.886617+00:00"
    },
    {
      "id": "92a00bef3fd3",
      "title": "Now Available on Steam - Kodon",
      "link": "https://store.steampowered.com/news/213793/",
      "source": "Steam",
      "hype_score": 0,
      "signals": [],
      "category": "indie",
      "fetched": "2026-05-22T03:59:31.886625+00:00"
    },
    {
      "id": "9a3196e2f7fd",
      "title": "Now Available on Steam - RAILGRADE, 25% off!",
      "link": "https://store.steampowered.com/news/210653/",
      "source": "Steam",
      "hype_score": 0,
      "signals": [],
      "category": "indie",
      "fetched": "2026-05-22T03:59:31.886632+00:00"
    },
    {
      "id": "e87308887a8f",
      "title": "Now Available on Steam - Kynseed, 10% off!",
      "link": "https://store.steampowered.com/news/166893/",
      "source": "Steam",
      "hype_score": 0,
      "signals": [],
      "category": "indie",
      "fetched": "2026-05-22T03:59:31.886639+00:00"
    },
    {
      "id": "c277d396afc5",
      "title": "Now Available on Steam - Quake Champions",
      "link": "https://store.steampowered.com/news/142057/",
      "source": "Steam",
      "hype_score": 0,
      "signals": [],
      "category": "indie",
      "fetched": "2026-05-22T03:59:31.886653+00:00"
    },
    {
      "id": "bea57a2cad4b",
      "title": "Now Available on Steam - Good Company, 20% off!",
      "link": "https://store.steampowered.com/news/139789/",
      "source": "Steam",
      "hype_score": 0,
      "signals": [],
      "category": "indie",
      "fetched": "2026-05-22T03:59:31.886674+00:00"
    },
    {
      "id": "2b33a0d2e849",
      "title": "Now Available on Steam - Raft, 15% off!",
      "link": "https://store.steampowered.com/news/139741/",
      "source": "Steam",
      "hype_score": 0,
      "signals": [],
      "category": "indie",
      "fetched": "2026-05-22T03:59:31.886682+00:00"
    },
    {
      "id": "76486910b88d",
      "title": "Now Available on Steam - Factory Town",
      "link": "https://store.steampowered.com/news/101463/",
      "source": "Steam",
      "hype_score": 0,
      "signals": [],
      "category": "indie",
      "fetched": "2026-05-22T03:59:31.886689+00:00"
    },
    {
      "id": "525c2d8d9276",
      "title": "Now Available on Steam - Ruined King: A League of Legends Story™",
      "link": "https://store.steampowered.com/news/101398/",
      "source": "Steam",
      "hype_score": 0,
      "signals": [],
      "category": "indie",
      "fetched": "2026-05-22T03:59:31.886702+00:00"
    },
    {
      "id": "6dd4031699c9",
      "title": "Now Available on Steam - Killsquad, 20% off!",
      "link": "https://store.steampowered.com/news/90261/",
      "source": "Steam",
      "hype_score": 0,
      "signals": [],
      "category": "indie",
      "fetched": "2026-05-22T03:59:31.886711+00:00"
    },
    {
      "id": "1ee37b397fe1",
      "title": "Now Available on Steam - Legion TD 2 - Multiplayer Tower Defense",
      "link": "https://store.steampowered.com/news/89382/",
      "source": "Steam",
      "hype_score": 0,
      "signals": [],
      "category": "indie",
      "fetched": "2026-05-22T03:59:31.886719+00:00"
    },
    {
      "id": "ad5d4c144ee8",
      "title": "Now Available on Steam - Rec Room",
      "link": "https://store.steampowered.com/news/88237/",
      "source": "Steam",
      "hype_score": 0,
      "signals": [],
      "category": "indie",
      "fetched": "2026-05-22T03:59:31.886727+00:00"
    },
    {
      "id": "b6983916f0e2",
      "title": "Now Available on Steam - Clone Drone in the Danger Zone, 15% off!",
      "link": "https://store.steampowered.com/news/86805/",
      "source": "Steam",
      "hype_score": 0,
      "signals": [],
      "category": "indie",
      "fetched": "2026-05-22T03:59:31.886734+00:00"
    },
    {
      "id": "678818361f61",
      "title": "Now Available on Steam - Totally Accurate Battle Simulator",
      "link": "https://store.steampowered.com/news/82651/",
      "source": "Steam",
      "hype_score": 0,
      "signals": [],
      "category": "indie",
      "fetched": "2026-05-22T03:59:31.886741+00:00"
    },
    {
      "id": "c675b163cce1",
      "title": "New DLC Available - ROMANCE OF THE THREE KINGDOMS XIV: Diplomacy and Strategy Expansion Pack, 10% off!",
      "link": "https://store.steampowered.com/news/78720/",
      "source": "Steam",
      "hype_score": 0,
      "signals": [],
      "category": "indie",
      "fetched": "2026-05-22T03:59:31.886748+00:00"
    },
    {
      "id": "c9c572f120aa",
      "title": "Now Available on Steam - Dreadlands, 20% off!",
      "link": "https://store.steampowered.com/news/77616/",
      "source": "Steam",
      "hype_score": 0,
      "signals": [],
      "category": "indie",
      "fetched": "2026-05-22T03:59:31.886921+00:00"
    },
    {
      "id": "8eccb8790dfa",
      "title": "Now Available on Steam - Kine, 34% off!",
      "link": "https://store.steampowered.com/news/76709/",
      "source": "Steam",
      "hype_score": 0,
      "signals": [],
      "category": "indie",
      "fetched": "2026-05-22T03:59:31.886929+00:00"
    },
    {
      "id": "cda881eac7a7",
      "title": "Left 4 Dead - Update",
      "link": "https://store.steampowered.com/news/270398/",
      "source": "Steam",
      "hype_score": 0,
      "signals": [],
      "category": "indie",
      "fetched": "2026-05-22T03:59:31.886938+00:00"
    },
    {
      "id": "88175c17fa62",
      "title": "Team Fortress 2 Update Released",
      "link": "https://store.steampowered.com/news/265516/",
      "source": "Steam",
      "hype_score": 0,
      "signals": [],
      "category": "indie",
      "fetched": "2026-05-22T03:59:31.886947+00:00"
    },
    {
      "id": "3cbb14087f77",
      "title": "Love at The Milky Way Diner - Demo",
      "link": "https://clumsycatstudio.itch.io/love-at-the-milky-way-diner-demo",
      "source": "itch.io",
      "hype_score": 0,
      "signals": [],
      "category": "indie",
      "fetched": "2026-05-22T03:59:31.886958+00:00"
    },
    {
      "id": "a922816cf638",
      "title": "Love at The Milky Way Diner - Early Access$13.99",
      "link": "https://clumsycatstudio.itch.io/love-at-the-milky-way-diner",
      "source": "itch.io",
      "hype_score": 0,
      "signals": [],
      "category": "indie",
      "fetched": "2026-05-22T03:59:31.886965+00:00"
    },
    {
      "id": "9eaf94146a77",
      "title": "Tavern Talk Stories: Dreamwalker",
      "link": "https://gentle-troll.itch.io/tavern-talk-stories-dreamwalker",
      "source": "itch.io",
      "hype_score": 0,
      "signals": [],
      "category": "indie",
      "fetched": "2026-05-22T03:59:31.886973+00:00"
    },
    {
      "id": "f40cc0b2d150",
      "title": "SOLAR DESCENT$2.99-50%",
      "link": "https://qhoang.itch.io/solar-descent",
      "source": "itch.io",
      "hype_score": 0,
      "signals": [],
      "category": "indie",
      "fetched": "2026-05-22T03:59:31.886981+00:00"
    },
    {
      "id": "e647a6ab888e",
      "title": "CORRODE",
      "link": "https://iamderlencer.itch.io/corrode",
      "source": "itch.io",
      "hype_score": 0,
      "signals": [],
      "category": "indie",
      "fetched": "2026-05-22T03:59:31.886990+00:00"
    },
    {
      "id": "46093741c25f",
      "title": "Night of the Idle Horde",
      "link": "https://bohfam.itch.io/night-of-the-idle-horde",
      "source": "itch.io",
      "hype_score": 0,
      "signals": [],
      "category": "indie",
      "fetched": "2026-05-22T03:59:31.886998+00:00"
    },
    {
      "id": "b6c90a23e2bb",
      "title": "Hangover Gallery",
      "link": "https://mikeklubnika.itch.io/hangover-gallery",
      "source": "itch.io",
      "hype_score": 0,
      "signals": [],
      "category": "indie",
      "fetched": "2026-05-22T03:59:31.887007+00:00"
    },
    {
      "id": "6b93d069d8cc",
      "title": "Can I Come In?",
      "link": "https://sheol01.itch.io/can-i-come-in",
      "source": "itch.io",
      "hype_score": 0,
      "signals": [],
      "category": "indie",
      "fetched": "2026-05-22T03:59:31.887015+00:00"
    },
    {
      "id": "6936a830e01d",
      "title": "Atic Atac 3D",
      "link": "https://stephensmith.itch.io/atic-atac-3d",
      "source": "itch.io",
      "hype_score": 0,
      "signals": [],
      "category": "indie",
      "fetched": "2026-05-22T03:59:31.887035+00:00"
    },
    {
      "id": "da0e01f399ad",
      "title": "The MachinEGG",
      "link": "https://quantumgames-studio.itch.io/the-machinegg",
      "source": "itch.io",
      "hype_score": 0,
      "signals": [],
      "category": "indie",
      "fetched": "2026-05-22T03:59:31.887046+00:00"
    },
    {
      "id": "0bd63eac9d41",
      "title": "Bloodbane: The Crimson Nocturne [Post-Ludum ver.]",
      "link": "https://hvdr02.itch.io/bloodbane-the-crimson-nocturne-post-ludum-ver",
      "source": "itch.io",
      "hype_score": 0,
      "signals": [],
      "category": "indie",
      "fetched": "2026-05-22T03:59:31.887054+00:00"
    },
    {
      "id": "30142c6f5337",
      "title": "IMPOSSIBLE MISSION 3 (C64)$6.99",
      "link": "https://psytronik.itch.io/im3-c64",
      "source": "itch.io",
      "hype_score": 0,
      "signals": [],
      "category": "indie",
      "fetched": "2026-05-22T03:59:31.887063+00:00"
    },
    {
      "id": "9e3b748ed2ae",
      "title": "Celsius Strays",
      "link": "https://cowcat.itch.io/celsius-strays",
      "source": "itch.io",
      "hype_score": 0,
      "signals": [],
      "category": "indie",
      "fetched": "2026-05-22T03:59:31.887072+00:00"
    },
    {
      "id": "069788f718a5",
      "title": "Riftborne$6.79-15%",
      "link": "https://riftborne.itch.io/riftborne",
      "source": "itch.io",
      "hype_score": 0,
      "signals": [],
      "category": "indie",
      "fetched": "2026-05-22T03:59:31.887080+00:00"
    },
    {
      "id": "ad54d5e469f3",
      "title": "Shadowbounty",
      "link": "https://radcodex.itch.io/shadowbounty",
      "source": "itch.io",
      "hype_score": 0,
      "signals": [],
      "category": "indie",
      "fetched": "2026-05-22T03:59:31.887089+00:00"
    },
    {
      "id": "4a70aa464684",
      "title": "TAXI BOY for GameBoy-GameBoyColor by PCNONOGames3.90â¬",
      "link": "https://pcnonogames.itch.io/taxi-boy-for-gameboy-by-pcnonogames",
      "source": "itch.io",
      "hype_score": 0,
      "signals": [],
      "category": "indie",
      "fetched": "2026-05-22T03:59:31.887099+00:00"
    },
    {
      "id": "18ad1a965f61",
      "title": "APEX-11: Shadow Protocol",
      "link": "https://r-goulart.itch.io/apex-11-shadow-protocol",
      "source": "itch.io",
      "hype_score": 0,
      "signals": [],
      "category": "indie",
      "fetched": "2026-05-22T03:59:31.887108+00:00"
    },
    {
      "id": "f287ca423cf4",
      "title": "The Indigo Parallel$3.76-71%",
      "link": "https://chris-danelon.itch.io/the-indigo-parallel",
      "source": "itch.io",
      "hype_score": 0,
      "signals": [],
      "category": "indie",
      "fetched": "2026-05-22T03:59:31.887117+00:00"
    },
    {
      "id": "0ca4d4d3fae7",
      "title": "Dynamine",
      "link": "https://hexagonnico.itch.io/dynamine",
      "source": "itch.io",
      "hype_score": 0,
      "signals": [],
      "category": "indie",
      "fetched": "2026-05-22T03:59:31.887126+00:00"
    },
    {
      "id": "029f511dc39b",
      "title": "CreepyDates",
      "link": "https://hahadit.itch.io/creepydates",
      "source": "itch.io",
      "hype_score": 0,
      "signals": [],
      "category": "indie",
      "fetched": "2026-05-22T03:59:31.887136+00:00"
    }
  ]
}